flagr/__init__.py
flagr/api_client.py
flagr/configuration.py
flagr/rest.py
flagr/api/__init__.py
flagr/api/constraint_api.py
flagr/api/distribution_api.py
flagr/api/evaluation_api.py
flagr/api/export_api.py
flagr/api/flag_api.py
flagr/api/health_api.py
flagr/api/segment_api.py
flagr/api/tag_api.py
flagr/api/variant_api.py
flagr/models/__init__.py
flagr/models/constraint.py
flagr/models/create_constraint_request.py
flagr/models/create_flag_request.py
flagr/models/create_segment_request.py
flagr/models/create_tag_request.py
flagr/models/create_variant_request.py
flagr/models/distribution.py
flagr/models/error.py
flagr/models/eval_context.py
flagr/models/eval_debug_log.py
flagr/models/eval_result.py
flagr/models/evaluation_batch_request.py
flagr/models/evaluation_batch_response.py
flagr/models/evaluation_entity.py
flagr/models/flag.py
flagr/models/flag_snapshot.py
flagr/models/health.py
flagr/models/put_distributions_request.py
flagr/models/put_flag_request.py
flagr/models/put_segment_reorder_request.py
flagr/models/put_segment_request.py
flagr/models/put_variant_request.py
flagr/models/segment.py
flagr/models/segment_debug_log.py
flagr/models/set_flag_enabled_request.py
flagr/models/tag.py
flagr/models/variant.py
test/__init__.py
test/test_constraint.py
test/test_constraint_api.py
test/test_create_constraint_request.py
test/test_create_flag_request.py
test/test_create_segment_request.py
test/test_create_tag_request.py
test/test_create_variant_request.py
test/test_distribution.py
test/test_distribution_api.py
test/test_error.py
test/test_eval_context.py
test/test_eval_debug_log.py
test/test_eval_result.py
test/test_evaluation_api.py
test/test_evaluation_batch_request.py
test/test_evaluation_batch_response.py
test/test_evaluation_entity.py
test/test_export_api.py
test/test_flag.py
test/test_flag_api.py
test/test_flag_snapshot.py
test/test_health.py
test/test_health_api.py
test/test_put_distributions_request.py
test/test_put_flag_request.py
flagr-1.1.10.dist-info/METADATA
flagr-1.1.10.dist-info/WHEEL
flagr-1.1.10.dist-info/top_level.txt
flagr-1.1.10.dist-info/RECORD
