Metadata-Version: 2.1
Name: flagr
Version: 1.1.10
Summary: Flagr
Home-page: https://github.com/checkr/pyflagr
Author: UNKNOWN
Author-email: UNKNOWN
License: UNKNOWN
Keywords: Swagger,Flagr
Platform: UNKNOWN
Requires-Dist: certifi (>=2017.4.17)
Requires-Dist: python-dateutil (>=2.1)
Requires-Dist: six (>=1.10)
Requires-Dist: urllib3 (>=1.23)
